cmdpkg/__init__.py
cmdpkg/_typing.py
cmdpkg/base.py
cmdpkg/command.py
cmdpkg/models.py
cmdpkg/process.py
cmdpkg/shell.py
cmdpkg/utils.py
cmdpkg-0.2.1.dist-info/LICENSE
cmdpkg-0.2.1.dist-info/METADATA
cmdpkg-0.2.1.dist-info/WHEEL
cmdpkg-0.2.1.dist-info/RECORD
