Metadata-Version: 2.1
Name: cmdpkg
Version: 0.2.1
Summary: Run Commands In Different Ways
Home-page: https://github.com/DavOstx7/cmdpkg
License: MIT
Author: dav ost
Author-email: davidost2003@gmail.com
Requires-Python: >=3.6,<4.0
Classifier: License :: OSI Approved :: MIT License
Classifier: Programming Language :: Python :: 3
Classifier: Programming Language :: Python :: 3.6
Classifier: Programming Language :: Python :: 3.7
Classifier: Programming Language :: Python :: 3.8
Classifier: Programming Language :: Python :: 3.9
Classifier: Programming Language :: Python :: 3.10
Classifier: Programming Language :: Python :: 3.11
Requires-Dist: dataclasses (>=0.6,<0.7)
Project-URL: Repository, https://github.com/DavOstx7/cmdpkg
